streamlit_mui/__init__.py
streamlit_mui/hello.py
streamlit_mui/component/__init__.py
streamlit_mui/component/frontend/build/asset-manifest.json
streamlit_mui/component/frontend/build/bootstrap.min.css
streamlit_mui/component/frontend/build/index.html
streamlit_mui/component/frontend/build/static/js/main.a4e48aa5.js
streamlit_mui/component/frontend/build/static/js/main.a4e48aa5.js.LICENSE.txt
streamlit_mui/component/frontend/build/static/js/main.a4e48aa5.js.map
streamlit_mui/component/frontend/build/static/js/main.e94c2016.js
streamlit_mui/component/frontend/build/static/js/main.e94c2016.js.LICENSE.txt
streamlit_mui/component/frontend/build/static/js/main.e94c2016.js.map
streamlit_mui/util/__init__.py
streamlit_mui/widgets/__init__.py
streamlit_mui/widgets/button/__init__.py
streamlit_mui/widgets/button/icon_button.py
streamlit_mui/widgets/chart/__init__.py
streamlit_mui/widgets/chart/bar_chart/__init__.py
streamlit_mui-1.0.4.dist-info/METADATA
streamlit_mui-1.0.4.dist-info/WHEEL
streamlit_mui-1.0.4.dist-info/entry_points.txt
streamlit_mui-1.0.4.dist-info/top_level.txt
streamlit_mui-1.0.4.dist-info/RECORD
