Metadata-Version: 2.1
Name: streamlit_mui
Version: 1.0.4
Summary: Streamlit module which provides implementation of various Material UI components
Author: Dilip Thakkar
Author-email: dilip.thakkar.eng@gmail.com
Requires-Python: >=3.9.0
Requires-Dist: streamlit>=1.36.0
